public_wrappers/ConfigError.py
public_wrappers/__init__.py
public_wrappers/__main__.py
public_wrappers/config.py
public_wrappers/wrappers.py
public_wrappers-0.4.0.dist-info/METADATA
public_wrappers-0.4.0.dist-info/RECORD
public_wrappers-0.4.0.dist-info/WHEEL
public_wrappers-0.4.0.dist-info/entry_points.txt
public_wrappers-0.4.0.dist-info/top_level.txt
