Metadata-Version: 2.1
Name: public-wrappers
Version: 0.4.0
Summary: Wrap selected public programs from conda/virtualenv environments
Home-page: https://github.com/tesujimath/public-wrappers
Author: Simon Guest
Author-email: simon.guest@tesujimath.org
License: MIT
Platform: UNKNOWN
Classifier: Development Status :: 4 - Beta
Classifier: Environment :: Console
Classifier: Intended Audience :: System Administrators
Classifier: License :: OSI Approved :: MIT License
Classifier: Operating System :: POSIX :: Linux
Classifier: Programming Language :: Python :: 2.7
Classifier: Programming Language :: Python :: 3
Classifier: Topic :: System :: Systems Administration
Classifier: Topic :: Utilities
Requires-Python: >=2.7
Requires-Dist: exec-wrappers
Requires-Dist: future
Requires-Dist: pytoml
